{
  "configVersion": 1,
  "timestamp": 1651196549407,
  "index": "/index.html",
  "assetGroups": [
    {
      "name": "app",
      "installMode": "prefetch",
      "updateMode": "prefetch",
      "cacheQueryOptions": {
        "ignoreVary": true
      },
      "urls": [
        "/favicon.ico",
        "/index.html",
        "/main-es2017.e24d530e7c5a566ce88c.js",
        "/main-es5.e24d530e7c5a566ce88c.js",
        "/manifest.webmanifest",
        "/polyfills-es2017.34b6caf9ced032a6162c.js",
        "/polyfills-es5.3e7e4d36c9139be1210b.js",
        "/runtime-es2017.d58256d0ff91969980af.js",
        "/runtime-es5.d58256d0ff91969980af.js",
        "/styles.6cdb2484d5238258e11b.css"
      ],
      "patterns": []
    },
    {
      "name": "assets",
      "installMode": "lazy",
      "updateMode": "prefetch",
      "cacheQueryOptions": {
        "ignoreVary": true
      },
      "urls": [
        "/assets/deezer-icon.svg",
        "/assets/deezer-logo.png",
        "/assets/i18n/en.json",
        "/assets/i18n/fr.json",
        "/assets/icons/icon-128x128.png",
        "/assets/icons/icon-144x144.png",
        "/assets/icons/icon-152x152.png",
        "/assets/icons/icon-192x192.png",
        "/assets/icons/icon-384x384.png",
        "/assets/icons/icon-512x512.png",
        "/assets/icons/icon-72x72.png",
        "/assets/icons/icon-96x96.png",
        "/assets/sonor-logo.png",
        "/assets/spotify-icon.svg",
        "/assets/spotify-logo-black.png",
        "/assets/spotify-logo-green.png",
        "/assets/spotify-logo-white.png"
      ],
      "patterns": []
    }
  ],
  "dataGroups": [],
  "hashTable": {
    "/assets/deezer-icon.svg": "ab9453088fd96dd25613b6927487f287037e4ebf",
    "/assets/deezer-logo.png": "58bb3cf2a308b2bb4f1cb2520978eb7bd8ddb21e",
    "/assets/i18n/en.json": "8d8544cab8d92fba9c610205bb181a3beaa6b2e9",
    "/assets/i18n/fr.json": "50827f3ec689ec02908177c7f786274e646a058e",
    "/assets/icons/icon-128x128.png": "dae3b6ed49bdaf4327b92531d4b5b4a5d30c7532",
    "/assets/icons/icon-144x144.png": "b0bd89982e08f9bd2b642928f5391915b74799a7",
    "/assets/icons/icon-152x152.png": "7479a9477815dfd9668d60f8b3b2fba709b91310",
    "/assets/icons/icon-192x192.png": "1abd80d431a237a853ce38147d8c63752f10933b",
    "/assets/icons/icon-384x384.png": "329749cd6393768d3131ed6304c136b1ca05f2fd",
    "/assets/icons/icon-512x512.png": "559d9c4318b45a1f2b10596bbb4c960fe521dbcc",
    "/assets/icons/icon-72x72.png": "c457e56089a36952cd67156f9996bc4ce54a5ed9",
    "/assets/icons/icon-96x96.png": "3914125a4b445bf111c5627875fc190f560daa41",
    "/assets/sonor-logo.png": "557a173e3647c834618c94102ab27bb0d3721159",
    "/assets/spotify-icon.svg": "69af3394cf5ae3d542a695ac8d65eb65e160d3c1",
    "/assets/spotify-logo-black.png": "c972e835a6ee944410d5b2b27a8ca4e537ed83ef",
    "/assets/spotify-logo-green.png": "7f52082faaaab03b7c72ac8ee01be8c100fce09c",
    "/assets/spotify-logo-white.png": "b2ca5d63d322953dba109cbc3a2430fbd4dbe803",
    "/favicon.ico": "22f6a4a3bcaafafb0254e0f2fa4ceb89e505e8b2",
    "/index.html": "58c90f2ec3bb583d5debacaf29135f9c97d8c9ae",
    "/main-es2017.e24d530e7c5a566ce88c.js": "10c7fbbd967ed4570314c870df976c430a90ff07",
    "/main-es5.e24d530e7c5a566ce88c.js": "a316d8fa47d90c5f3913ffebdd5d799e83422907",
    "/manifest.webmanifest": "58377212ef34b112fff1fb8782ec0e2f930f65da",
    "/polyfills-es2017.34b6caf9ced032a6162c.js": "10deaf207b6bc7e9b831b315acf00fa5f8533d95",
    "/polyfills-es5.3e7e4d36c9139be1210b.js": "a46728b41726499c5611eac9e63bd358eb6b060a",
    "/runtime-es2017.d58256d0ff91969980af.js": "3f1373948be4d0d516ba0a42ca294709a7ec9f7b",
    "/runtime-es5.d58256d0ff91969980af.js": "3f1373948be4d0d516ba0a42ca294709a7ec9f7b",
    "/styles.6cdb2484d5238258e11b.css": "449f754277df1709de399246f41c9be9ffe30d6c"
  },
  "navigationUrls": [
    {
      "positive": true,
      "regex": "^\\/.*$"
    },
    {
      "positive": false,
      "regex": "^\\/(?:.+\\/)?[^/]*\\.[^/]*$"
    },
    {
      "positive": false,
      "regex": "^\\/(?:.+\\/)?[^/]*__[^/]*$"
    },
    {
      "positive": false,
      "regex": "^\\/(?:.+\\/)?[^/]*__[^/]*\\/.*$"
    }
  ],
  "navigationRequestStrategy": "performance"
}